pipecat/__init__.py
pipecat/py.typed
pipecat/adapters/__init__.py
pipecat/adapters/base_llm_adapter.py
pipecat/adapters/schemas/__init__.py
pipecat/adapters/schemas/direct_function.py
pipecat/adapters/schemas/function_schema.py
pipecat/adapters/schemas/tools_schema.py
pipecat/adapters/services/__init__.py
pipecat/adapters/services/anthropic_adapter.py
pipecat/adapters/services/aws_nova_sonic_adapter.py
pipecat/adapters/services/bedrock_adapter.py
pipecat/adapters/services/gemini_adapter.py
pipecat/adapters/services/open_ai_adapter.py
pipecat/adapters/services/open_ai_realtime_adapter.py
pipecat/audio/__init__.py
pipecat/audio/utils.py
pipecat/audio/filters/__init__.py
pipecat/audio/filters/base_audio_filter.py
pipecat/audio/filters/koala_filter.py
pipecat/audio/filters/krisp_filter.py
pipecat/audio/filters/noisereduce_filter.py
pipecat/audio/interruptions/__init__.py
pipecat/audio/interruptions/base_interruption_strategy.py
pipecat/audio/interruptions/min_words_interruption_strategy.py
pipecat/audio/mixers/__init__.py
pipecat/audio/mixers/base_audio_mixer.py
pipecat/audio/mixers/soundfile_mixer.py
pipecat/audio/resamplers/__init__.py
pipecat/audio/resamplers/base_audio_resampler.py
pipecat/audio/resamplers/resampy_resampler.py
pipecat/audio/resamplers/soxr_resampler.py
pipecat/audio/resamplers/soxr_stream_resampler.py
pipecat/audio/turn/__init__.py
pipecat/audio/turn/base_turn_analyzer.py
pipecat/audio/turn/smart_turn/__init__.py
pipecat/audio/turn/smart_turn/base_smart_turn.py
pipecat/audio/turn/smart_turn/fal_smart_turn.py
pipecat/audio/turn/smart_turn/http_smart_turn.py
pipecat/audio/turn/smart_turn/local_coreml_smart_turn.py
pipecat/audio/turn/smart_turn/local_smart_turn.py
pipecat/audio/turn/smart_turn/local_smart_turn_v2.py
pipecat/audio/vad/__init__.py
pipecat/audio/vad/silero.py
pipecat/audio/vad/vad_analyzer.py
pipecat/audio/vad/data/__init__.py
pipecat/audio/vad/data/silero_vad.onnx
pipecat/clocks/__init__.py
pipecat/clocks/base_clock.py
pipecat_ai_websocket-0.0.77.dev177.dist-info/licenses/LICENSE
pipecat_ai_websocket-0.0.77.dev177.dist-info/METADATA
pipecat_ai_websocket-0.0.77.dev177.dist-info/WHEEL
pipecat_ai_websocket-0.0.77.dev177.dist-info/top_level.txt
pipecat_ai_websocket-0.0.77.dev177.dist-info/RECORD
